less_squares/__init__.py
less_squares/less_squares.py
less_squares/performance_demonstration.py
less_squares-0.1.4.dist-info/LICENSE
less_squares-0.1.4.dist-info/METADATA
less_squares-0.1.4.dist-info/WHEEL
less_squares-0.1.4.dist-info/top_level.txt
less_squares-0.1.4.dist-info/RECORD
