Metadata-Version: 2.2
Name: less_squares
Version: 0.1.4
Summary: A fast O(nm) iterative least squares solution
Home-page: https://github.com/Christopher-DArcy/less_squares
Author: Christopher D'Arcy
Author-email: chris@scigood.com
License: GNU General Public License v3 (GPLv3)
Classifier: Programming Language :: Python :: 3
Classifier: Programming Language :: Python :: 3.8
Classifier: License :: OSI Approved :: GNU General Public License v3 (GPLv3)
Classifier: Operating System :: OS Independent
Requires-Python: >=3.8
License-File: LICENSE
Requires-Dist: numpy
Provides-Extra: test
Requires-Dist: unittest; python_version >= "3.8" and extra == "test"
Dynamic: author
Dynamic: author-email
Dynamic: classifier
Dynamic: description
Dynamic: description-content-type
Dynamic: home-page
Dynamic: license
Dynamic: provides-extra
Dynamic: requires-dist
Dynamic: requires-python
Dynamic: summary
